raftnode/__init__.py
raftnode/cli.py
raftnode/config.py
raftnode/election.py
raftnode/log.py
raftnode/raftnode.py
raftnode/store.py
raftnode/transport.py
raftnode/datastore/Idatastore.py
raftnode/datastore/__init__.py
raftnode/datastore/memory.py
raftnode/datastore/rocks.py
raftnode-0.1.2.dist-info/AUTHORS.rst
raftnode-0.1.2.dist-info/LICENSE
raftnode-0.1.2.dist-info/METADATA
raftnode-0.1.2.dist-info/WHEEL
raftnode-0.1.2.dist-info/entry_points.txt
raftnode-0.1.2.dist-info/top_level.txt
raftnode-0.1.2.dist-info/RECORD
