Metadata-Version: 2.1
Name: raftnode
Version: 0.1.2
Summary: RAFT consensus algorithm implementation
Home-page: https://github.com/shrinivdeshmukh/raftnode
Author: Shrinivas Vijay Deshmukh
Author-email: shrinivas.deshmukh11@gmail.com
License: MIT license
Keywords: raftnode
Platform: UNKNOWN
Classifier: Development Status :: 2 - Pre-Alpha
Classifier: Intended Audience :: Developers
Classifier: License :: OSI Approved :: MIT License
Classifier: Natural Language :: English
Classifier: Programming Language :: Python :: 3
Classifier: Programming Language :: Python :: 3.6
Classifier: Programming Language :: Python :: 3.7
Classifier: Programming Language :: Python :: 3.8
Requires-Python: >=3.6
Requires-Dist: fabulous (==0.4.0)
Provides-Extra: rocksdb
Requires-Dist: rocksdb (==0.7.0) ; extra == 'rocksdb'
